MANIFEST.in
pyproject.toml
setup.py
build_tools/VERSION.txt
build_tools/__init__.py
build_tools/build_ext.py
build_tools/jax.py
build_tools/pytorch.py
build_tools/te_version.py
build_tools/utils.py
build_tools/__pycache__/__init__.cpython-310.pyc
build_tools/__pycache__/build_ext.cpython-310.pyc
build_tools/__pycache__/jax.cpython-310.pyc
build_tools/__pycache__/te_version.cpython-310.pyc
build_tools/__pycache__/utils.cpython-310.pyc
build_tools/wheel_utils/Dockerfile.aarch
build_tools/wheel_utils/Dockerfile.x86
build_tools/wheel_utils/build_wheels.sh
build_tools/wheel_utils/launch_aarch.sh
build_tools/wheel_utils/launch_x86.sh
common_headers/common/common.h
common_headers/common/cudnn_utils.h
common_headers/common/nvtx.h
common_headers/common/utils.cuh
common_headers/common/activation/activation_template.h
common_headers/common/comm_gemm_overlap/userbuffers/ipcsocket.h
common_headers/common/comm_gemm_overlap/userbuffers/userbuffers.h
common_headers/common/fused_attn/fused_attn_f16_arbitrary_seqlen.h
common_headers/common/fused_attn/fused_attn_f16_max512_seqlen.h
common_headers/common/fused_attn/fused_attn_fp8.h
common_headers/common/fused_attn/utils.h
common_headers/common/fused_router/utils.h
common_headers/common/gemm/config.h
common_headers/common/gemm/cutlass_grouped_gemm.cuh
common_headers/common/include/transformer_engine/activation.h
common_headers/common/include/transformer_engine/cast.h
common_headers/common/include/transformer_engine/cast_transpose_noop.h
common_headers/common/include/transformer_engine/comm_gemm.h
common_headers/common/include/transformer_engine/comm_gemm_overlap.h
common_headers/common/include/transformer_engine/cudnn.h
common_headers/common/include/transformer_engine/dropout.h
common_headers/common/include/transformer_engine/fused_attn.h
common_headers/common/include/transformer_engine/fused_rope.h
common_headers/common/include/transformer_engine/fused_router.h
common_headers/common/include/transformer_engine/gemm.h
transformer_engine_jax.egg-info/PKG-INFO
transformer_engine_jax.egg-info/SOURCES.txt
transformer_engine_jax.egg-info/dependency_links.txt
transformer_engine_jax.egg-info/requires.txt
transformer_engine_jax.egg-info/top_level.txt